azure/mgmt/iotfirmwaredefense/__init__.py
azure/mgmt/iotfirmwaredefense/_client.py
azure/mgmt/iotfirmwaredefense/_configuration.py
azure/mgmt/iotfirmwaredefense/_patch.py
azure/mgmt/iotfirmwaredefense/_validation.py
azure/mgmt/iotfirmwaredefense/_version.py
azure/mgmt/iotfirmwaredefense/py.typed
azure/mgmt/iotfirmwaredefense/_utils/__init__.py
azure/mgmt/iotfirmwaredefense/_utils/model_base.py
azure/mgmt/iotfirmwaredefense/_utils/serialization.py
azure/mgmt/iotfirmwaredefense/aio/__init__.py
azure/mgmt/iotfirmwaredefense/aio/_client.py
azure/mgmt/iotfirmwaredefense/aio/_configuration.py
azure/mgmt/iotfirmwaredefense/aio/_patch.py
azure/mgmt/iotfirmwaredefense/aio/operations/__init__.py
azure/mgmt/iotfirmwaredefense/aio/operations/_operations.py
azure/mgmt/iotfirmwaredefense/aio/operations/_patch.py
azure/mgmt/iotfirmwaredefense/models/__init__.py
azure/mgmt/iotfirmwaredefense/models/_enums.py
azure/mgmt/iotfirmwaredefense/models/_models.py
azure/mgmt/iotfirmwaredefense/models/_patch.py
azure/mgmt/iotfirmwaredefense/operations/__init__.py
azure/mgmt/iotfirmwaredefense/operations/_operations.py
azure/mgmt/iotfirmwaredefense/operations/_patch.py
azure_mgmt_iotfirmwaredefense-2.0.0.dist-info/licenses/LICENSE
azure_mgmt_iotfirmwaredefense-2.0.0.dist-info/METADATA
azure_mgmt_iotfirmwaredefense-2.0.0.dist-info/WHEEL
azure_mgmt_iotfirmwaredefense-2.0.0.dist-info/top_level.txt
azure_mgmt_iotfirmwaredefense-2.0.0.dist-info/RECORD
